rayvision_utils/__init__.py
rayvision_utils/cmd.py
rayvision_utils/constants.py
rayvision_utils/utils.py
rayvision_utils/exception/__init__.py
rayvision_utils/exception/error_msg.py
rayvision_utils/exception/exception.py
rayvision_utils/exception/tips.py
rayvision_utils/exception/tips_code.py
rayvision_utils/tests/__init__.py
rayvision_utils/tests/conftest.py
rayvision_utils/tests/test_cmd.py
rayvision_utils/tests/test_exception.py
rayvision_utils/tests/test_tips.py
rayvision_utils/tests/test_utils.py
rayvision_utils-1.2.2.3.dist-info/METADATA
rayvision_utils-1.2.2.3.dist-info/WHEEL
rayvision_utils-1.2.2.3.dist-info/top_level.txt
rayvision_utils-1.2.2.3.dist-info/RECORD
