Metadata-Version: 2.1
Name: rayvision-utils
Version: 1.2.2.3
Summary: A Python API for Using Renderbus cloud rendering.
Home-page: https://github.com/renderbus/rayvision_utils
Author: Shenzhen Rayvision Technology Co., Ltd
Author-email: developer@rayvision.com
Classifier: Programming Language :: Python
Classifier: Programming Language :: Python :: 2
Classifier: Programming Language :: Python :: 3
Requires-Dist: rayvision-log >=0.3.3
Requires-Dist: rayvision-api >=1.0.1
Requires-Dist: future ==0.18.2
Requires-Dist: requests ==2.23.0
Requires-Dist: tenacity ==7.0.0
